autodistill_hls_geospatial/__init__.py
autodistill_hls_geospatial/hls_model.py
autodistill_hls_geospatial-0.1.0.dist-info/LICENSE
autodistill_hls_geospatial-0.1.0.dist-info/METADATA
autodistill_hls_geospatial-0.1.0.dist-info/WHEEL
autodistill_hls_geospatial-0.1.0.dist-info/top_level.txt
autodistill_hls_geospatial-0.1.0.dist-info/RECORD
