Metadata-Version: 2.1
Name: autodistill-hls-geospatial
Version: 0.1.0
Summary: Use the HLS Geospatial model made by NASA and IBM to generate masks for use in training a fine-tuned segmentation model.
Home-page: https://github.com/autodistill/autodistill-hls-geospatial
Author: Roboflow
Author-email: support@roboflow.com
Classifier: Programming Language :: Python :: 3
Classifier: License :: OSI Approved :: MIT License
Classifier: Operating System :: OS Independent
Requires-Python: >=3.7
License-File: LICENSE
Requires-Dist: autodistill
Requires-Dist: supervision
Requires-Dist: rasterio
Requires-Dist: mmcv-full ==1.5.0
Provides-Extra: dev
Requires-Dist: flake8 ; extra == 'dev'
Requires-Dist: black ==22.3.0 ; extra == 'dev'
Requires-Dist: isort ; extra == 'dev'
Requires-Dist: twine ; extra == 'dev'
Requires-Dist: pytest ; extra == 'dev'
Requires-Dist: wheel ; extra == 'dev'
